{
  "project_info": {
    "project_number": "521359123666",
    "project_id": "medicine-delivery-b47b4",
    "storage_bucket": "medicine-delivery-b47b4.firebasestorage.app"
  },
  "client": [
    {
      "client_info": {
        "mobilesdk_app_id": "1:521359123666:android:1ddae144e4518231dc790b",
        "android_client_info": {
          "package_name": "com.medicine.medicine_delivery"
        }
      },
      "oauth_client": [],
      "api_key": [
        {
          "current_key": "AIzaSyAHTv4ACeg62kRQlVv-hSG1sLVNJKJrp3w"
        }
      ],
      "services": {
        "appinvite_service": {
          "other_platform_oauth_client": []
        }
      }
    }
  ],
  "configuration_version": "1"
}